sapiopycommons/__init__.py
sapiopycommons/ai/__init__.py
sapiopycommons/ai/agent_service_base.py
sapiopycommons/ai/converter_service_base.py
sapiopycommons/ai/external_credentials.py
sapiopycommons/ai/protobuf_utils.py
sapiopycommons/ai/request_validation.py
sapiopycommons/ai/server.py
sapiopycommons/ai/test_client.py
sapiopycommons/ai/protoapi/agent/agent_pb2.py
sapiopycommons/ai/protoapi/agent/agent_pb2.pyi
sapiopycommons/ai/protoapi/agent/agent_pb2_grpc.py
sapiopycommons/ai/protoapi/agent/entry_pb2.py
sapiopycommons/ai/protoapi/agent/entry_pb2.pyi
sapiopycommons/ai/protoapi/agent/entry_pb2_grpc.py
sapiopycommons/ai/protoapi/agent/item/item_container_pb2.py
sapiopycommons/ai/protoapi/agent/item/item_container_pb2.pyi
sapiopycommons/ai/protoapi/agent/item/item_container_pb2_grpc.py
sapiopycommons/ai/protoapi/externalcredentials/external_credentials_pb2.py
sapiopycommons/ai/protoapi/externalcredentials/external_credentials_pb2.pyi
sapiopycommons/ai/protoapi/externalcredentials/external_credentials_pb2_grpc.py
sapiopycommons/ai/protoapi/fielddefinitions/fields_pb2.py
sapiopycommons/ai/protoapi/fielddefinitions/fields_pb2.pyi
sapiopycommons/ai/protoapi/fielddefinitions/fields_pb2_grpc.py
sapiopycommons/ai/protoapi/fielddefinitions/velox_field_def_pb2.py
sapiopycommons/ai/protoapi/fielddefinitions/velox_field_def_pb2.pyi
sapiopycommons/ai/protoapi/fielddefinitions/velox_field_def_pb2_grpc.py
sapiopycommons/ai/protoapi/pipeline/step_output_pb2.py
sapiopycommons/ai/protoapi/pipeline/step_output_pb2.pyi
sapiopycommons/ai/protoapi/pipeline/step_output_pb2_grpc.py
sapiopycommons/ai/protoapi/pipeline/step_pb2.py
sapiopycommons/ai/protoapi/pipeline/step_pb2.pyi
sapiopycommons/ai/protoapi/pipeline/step_pb2_grpc.py
sapiopycommons/ai/protoapi/pipeline/converter/converter_pb2.py
sapiopycommons/ai/protoapi/pipeline/converter/converter_pb2.pyi
sapiopycommons/ai/protoapi/pipeline/converter/converter_pb2_grpc.py
sapiopycommons/ai/protoapi/pipeline/script/script_pb2.py
sapiopycommons-36.0.7.25.9.1.dist-info/METADATA
sapiopycommons-36.0.7.25.9.1.dist-info/WHEEL
sapiopycommons-36.0.7.25.9.1.dist-info/licenses/LICENSE
sapiopycommons-36.0.7.25.9.1.dist-info/RECORD
