Metadata-Version: 2.3
Name: sapiopycommons
Version: 36.0.7.25.9.1
Summary: Official Sapio Python API Utilities Package
Project-URL: Homepage, https://github.com/sapiosciences
Author-email: Jonathan Steck <jsteck@sapiosciences.com>, Yechen Qiao <yqiao@sapiosciences.com>
License: MPL-2.0
Keywords: eln,lims,rest,sapio
Classifier: Development Status :: 5 - Production/Stable
Classifier: Intended Audience :: Developers
Classifier: Intended Audience :: Healthcare Industry
Classifier: Intended Audience :: Science/Research
Classifier: License :: OSI Approved :: Mozilla Public License 2.0 (MPL 2.0)
Classifier: Operating System :: OS Independent
Classifier: Programming Language :: Python :: 3.10
Classifier: Topic :: Scientific/Engineering :: Bio-Informatics
Classifier: Topic :: Software Development :: Libraries :: Python Modules
Requires-Python: >=3.10
Requires-Dist: databind>=4.5
Requires-Dist: sapiopylib>=2025.10.7.295
